6-4/user/src/top.v
module lock(clk, reset, b1, b2, b3, b4, open, error);
    input clk, reset, b1, b2, b3, b4;
    output open, error;

    parameter   IDLE    = 3'd0,
                S1      = 3'd1,
                S2      = 3'd2,
                S3      = 3'd3,
                S4      = 3'd4,
                OPEN    = 3'd5,
                ERROR   = 3'd6;

    reg [15:0]  buffer;
    reg [2:0]   state, next_state;

    reg [3:0] in;

    always @(*) begin
        case ({b1, b2, b3, b4})
            4'b1000 :
                in = 4'h1;
            4'b0100 :
                in = 4'h2;
            4'b0010 :
                in = 4'h3;
            4'b0001 :
                in = 4'h4;
            default :
                in = 4'b0;
        endcase
    end

    always @(posedge clk, negedge reset) begin
        if (reset == 1'b0)
            state <= IDLE;
        else 
            state <= next_state;
    end

    always @(posedge clk, negedge reset) begin
        if (reset == 1'b0)
            buffer <= 16'h0;
        else if ((state == OPEN) || (state == ERROR))
            buffer <= 16'h0;
        else if (in != 4'b0)
            buffer <= {buffer[11:0], in};
    end

    always @(*) begin
        case (state)
            IDLE :
                if (in != 4'b0)
                    next_state = S1;
                else
                    next_state = IDLE;
            S1 :
                if (in != 4'b0)
                    next_state = S2;
                else
                    next_state = S1;
            S2 :
                if (in != 4'b0)
                    next_state = S3;
                else
                    next_state = S2;
            S3 :
                if (in != 4'b0)
                    next_state = S4;
                else
                    next_state = S3;
            S4 :
                if ((buffer == 16'h2431) || (buffer == 16'h1443))
                    next_state = OPEN;
                else
                    next_state = ERROR;
            OPEN :
                next_state = OPEN;
            ERROR :
                next_state = ERROR;
            default: 
                next_state = IDLE;
        endcase
    end

    assign open = (state == OPEN) ? 1'b1 : 1'b0;
    assign error = (state == ERROR) ? 1'b1 : 1'b0;
endmodule

6-4/user/sim/tb.v
`timescale 1ns/1ps

module tb (

);

    initial begin
       $dumpfile("wave.vcd");
       $dumpvars(0, tb);
       #10000 $finish;
    end

    wire 	open;
    wire 	error;

    reg clk = 0, reset = 1;
    always 
        #10 clk <= ~clk;

    initial begin
        #20 reset <= ~reset;
        #20 reset <= ~reset;
    end

    always @(*) begin
        if (open || error) begin
            #30 reset = 1'b0;
            #30 reset = 1'b1;
        end 
    end

    reg [2:0] in;
    wire b1, b2, b3, b4;

    always 
        #20 in <= {$random}%5;

    assign b1 = (in == 3'd1) ? 1'b1 : 1'b0;
    assign b2 = (in == 3'd2) ? 1'b1 : 1'b0;
    assign b3 = (in == 3'd3) ? 1'b1 : 1'b0;
    assign b4 = (in == 3'd4) ? 1'b1 : 1'b0;

    lock #(
        .IDLE  		( 3'd0 		),
        .S1    		( 3'd1 		),
        .S2    		( 3'd2 		),
        .S3    		( 3'd3 		),
        .S4    		( 3'd4 		),
        .OPEN  		( 3'd5 		),
        .ERROR 		( 3'd6 		))
    u_lock(
        //ports
        .clk   		( clk   		),
        .reset 		( reset 		),
        .b1    		( b1    		),
        .b2    		( b2    		),
        .b3    		( b3    		),
        .b4    		( b4    		),
        .open  		( open  		),
        .error 		( error 		)
    );

endmodule

6-4/wave.vcd
$date
	Sun Apr 17 11:02:40 2022
$end
$version
	Icarus Verilog
$end
$timescale
	1ps
$end
$scope module tb $end
$var wire 1 ! open $end
$var wire 1 " error $end
$var wire 1 # b4 $end
$var wire 1 $ b3 $end
$var wire 1 % b2 $end
$var wire 1 & b1 $end
$var reg 1 ' clk $end
$var reg 3 ( in [2:0] $end
$var reg 1 ) reset $end
$scope module u_lock $end
$var wire 1 & b1 $end
$var wire 1 % b2 $end
$var wire 1 $ b3 $end
$var wire 1 # b4 $end
$var wire 1 ' clk $end
$var wire 1 ) reset $end
$var wire 1 ! open $end
$var wire 1 " error $end
$var reg 16 * buffer [15:0] $end
$var reg 4 + in [3:0] $end
$var reg 3 , next_state [2:0] $end
$var reg 3 - state [2:0] $end
$upscope $end
$upscope $end
$enddefinitions $end
#0
$dumpvars
bx -
b0 ,
b0 +
bx *
1)
bx (
0'
x&
x%
x$
x#
x"
x!
$end
#10000
0!
0"
b0 -
1'
#20000
b0 *
b1 ,
b11 +
0&
0%
1$
0#
0'
b11 (
0)
#30000
1'
#40000
b10 +
1%
0$
0'
b10 (
1)
#50000
b10 ,
b10 *
b1 -
1'
#60000
0'
#70000
b11 ,
b10 -
b100010 *
1'
#80000
0'
#90000
b100 ,
b1000100010 *
b11 -
1'
#100000
0'
#110000
b110 ,
b100 -
b10001000100010 *
1'
#120000
0'
#130000
1"
b110 -
1'
#140000
b0 +
0%
0'
b0 (
#150000
b0 *
1'
#160000
b10 +
b1 ,
0"
1%
b0 -
0'
b10 (
0)
#170000
1'
#180000
b1 +
1&
0%
0'
b1 (
#190000
b10 ,
b1 *
b1 -
1'
1)
#200000
b100 +
0&
1#
0'
b100 (
#210000
b11 ,
b10 -
b10100 *
1'
#220000
b11 +
1$
0#
0'
b11 (
#230000
b100 ,
b101000011 *
b11 -
1'
#240000
b10 +
1%
0$
0'
b10 (
#250000
b110 ,
b100 -
b1010000110010 *
1'
#260000
b100 +
0%
1#
0'
b100 (
#270000
1"
b100001100100100 *
b110 -
1'
#280000
b10 +
1%
0#
0'
b10 (
#290000
b0 *
1'
#300000
b100 +
b1 ,
0"
0%
1#
b0 -
0'
b100 (
0)
#310000
1'
#320000
b1 +
1&
0#
0'
b1 (
#330000
b10 ,
b1 *
b1 -
1'
1)
#340000
b10 +
0&
1%
0'
b10 (
#350000
b11 ,
b10 -
b10010 *
1'
#360000
0'
#370000
b100 ,
b100100010 *
b11 -
1'
#380000
b11 ,
b0 +
0%
0'
b0 (
#390000
1'
#400000
0'
#410000
1'
#420000
b100 ,
b100 +
1#
0'
b100 (
#430000
b110 ,
b100 -
b1001000100100 *
1'
#440000
0'
#450000
1"
b10001001000100 *
b110 -
1'
#460000
b1 +
1&
0#
0'
b1 (
#470000
b0 *
1'
#480000
b0 +
b0 ,
0"
0&
b0 -
0'
b0 (
0)
#490000
1'
#500000
b1 ,
b11 +
1$
0'
b11 (
#510000
b10 ,
b11 *
b1 -
1'
1)
#520000
0'
#530000
b11 ,
b10 -
b110011 *
1'
#540000
b100 +
0$
1#
0'
b100 (
#550000
b100 ,
b1100110100 *
b11 -
1'
#560000
b11 +
1$
0#
0'
b11 (
#570000
b110 ,
b100 -
b11001101000011 *
1'
#580000
b100 +
0$
1#
0'
b100 (
#590000
1"
b11010000110100 *
b110 -
1'
#600000
0'
#610000
b0 *
1'
#620000
b11 +
b1 ,
0"
1$
0#
b0 -
0'
b11 (
0)
#630000
1'
#640000
b0 ,
b0 +
0$
0'
b0 (
#650000
1'
1)
#660000
b1 ,
b11 +
1$
0'
b11 (
#670000
b10 ,
b1 -
b11 *
1'
#680000
b1 +
1&
0$
0'
b1 (
#690000
b11 ,
b110001 *
b10 -
1'
#700000
b100 +
0&
1#
0'
b100 (
#710000
b100 ,
b11 -
b1100010100 *
1'
#720000
b1 +
1&
0#
0'
b1 (
#730000
b110 ,
b11000101000001 *
b100 -
1'
#740000
b10 +
0&
1%
0'
b10 (
#750000
1"
b110 -
b1010000010010 *
1'
#760000
b1 +
1&
0%
0'
b1 (
#770000
b0 *
1'
#780000
b1 ,
0"
b0 -
0'
0)
#790000
1'
#800000
b11 +
0&
1$
0'
b11 (
#810000
b10 ,
b1 -
b11 *
1'
1)
#820000
b1 ,
b0 +
0$
0'
b0 (
#830000
1'
#840000
0'
#850000
1'
#860000
b10 ,
b11 +
1$
0'
b11 (
#870000
b11 ,
b110011 *
b10 -
1'
#880000
b10 +
1%
0$
0'
b10 (
#890000
b100 ,
b11 -
b1100110010 *
1'
#900000
b1 +
1&
0%
0'
b1 (
#910000
b110 ,
b11001100100001 *
b100 -
1'
#920000
b100 +
0&
1#
0'
b100 (
#930000
1"
b110 -
b11001000010100 *
1'
#940000
b10 +
1%
0#
0'
b10 (
#950000
b0 *
1'
#960000
b0 +
b0 ,
0"
0%
b0 -
0'
b0 (
0)
#970000
1'
#980000
b1 ,
b1 +
1&
0'
b1 (
#990000
b10 ,
b1 -
b1 *
1'
1)
#1000000
b11 +
0&
1$
0'
b11 (
#1010000
b11 ,
b10011 *
b10 -
1'
#1020000
b1 +
1&
0$
0'
b1 (
#1030000
b100 ,
b11 -
b100110001 *
1'
#1040000
b11 ,
b0 +
0&
0'
b0 (
#1050000
1'
#1060000
b100 ,
b10 +
1%
0'
b10 (
#1070000
b110 ,
b100 -
b1001100010010 *
1'
#1080000
b100 +
0%
1#
0'
b100 (
#1090000
1"
b11000100100100 *
b110 -
1'
#1100000
b0 +
0#
0'
b0 (
#1110000
b0 *
1'
#1120000
b100 +
b1 ,
0"
1#
b0 -
0'
b100 (
0)
#1130000
1'
#1140000
b10 +
1%
0#
0'
b10 (
#1150000
b10 ,
b10 *
b1 -
1'
1)
#1160000
b1 +
1&
0%
0'
b1 (
#1170000
b11 ,
b10 -
b100001 *
1'
#1180000
0'
#1190000
b100 ,
b1000010001 *
b11 -
1'
#1200000
0'
#1210000
b110 ,
b100 -
b10000100010001 *
1'
#1220000
b100 +
0&
1#
0'
b100 (
#1230000
1"
b1000100010100 *
b110 -
1'
#1240000
0'
#1250000
b0 *
1'
#1260000
b11 +
b1 ,
0"
1$
0#
b0 -
0'
b11 (
0)
#1270000
1'
#1280000
0'
#1290000
b10 ,
b11 *
b1 -
1'
1)
#1300000
b1 +
1&
0$
0'
b1 (
#1310000
b11 ,
b10 -
b110001 *
1'
#1320000
b10 ,
b0 +
0&
0'
b0 (
#1330000
1'
#1340000
b11 ,
b1 +
1&
0'
b1 (
#1350000
b100 ,
b11 -
b1100010001 *
1'
#1360000
b100 +
0&
1#
0'
b100 (
#1370000
b110 ,
b11000100010100 *
b100 -
1'
#1380000
b10 +
1%
0#
0'
b10 (
#1390000
1"
b110 -
b1000101000010 *
1'
#1400000
b1 +
1&
0%
0'
b1 (
#1410000
b0 *
1'
#1420000
b11 +
b1 ,
0"
0&
1$
b0 -
0'
b11 (
0)
#1430000
1'
#1440000
b1 +
1&
0$
0'
b1 (
#1450000
b10 ,
b1 -
b1 *
1'
1)
#1460000
b100 +
0&
1#
0'
b100 (
#1470000
b11 ,
b10100 *
b10 -
1'
#1480000
b11 +
1$
0#
0'
b11 (
#1490000
b100 ,
b11 -
b101000011 *
1'
#1500000
b100 +
0$
1#
0'
b100 (
#1510000
b110 ,
b1010000110100 *
b100 -
1'
#1520000
b0 +
0#
0'
b0 (
#1530000
1"
b110 -
1'
#1540000
0'
#1550000
b0 *
1'
#1560000
b11 +
b1 ,
0"
1$
b0 -
0'
b11 (
0)
#1570000
1'
#1580000
0'
#1590000
b10 ,
b1 -
b11 *
1'
1)
#1600000
b100 +
0$
1#
0'
b100 (
#1610000
b11 ,
b110100 *
b10 -
1'
#1620000
0'
#1630000
b100 ,
b11 -
b1101000100 *
1'
#1640000
b10 +
1%
0#
0'
b10 (
#1650000
b110 ,
b11010001000010 *
b100 -
1'
#1660000
b1 +
1&
0%
0'
b1 (
#1670000
1"
b110 -
b100010000100001 *
1'
#1680000
b10 +
0&
1%
0'
b10 (
#1690000
b0 *
1'
#1700000
b1 +
b1 ,
0"
1&
0%
b0 -
0'
b1 (
0)
#1710000
1'
#1720000
b0 ,
b0 +
0&
0'
b0 (
#1730000
1'
1)
#1740000
0'
#1750000
1'
#1760000
b1 ,
b100 +
1#
0'
b100 (
#1770000
b10 ,
b1 -
b100 *
1'
#1780000
0'
#1790000
b11 ,
b1000100 *
b10 -
1'
#1800000
0'
#1810000
b100 ,
b11 -
b10001000100 *
1'
#1820000
b1 +
1&
0#
0'
b1 (
#1830000
b110 ,
b100010001000001 *
b100 -
1'
#1840000
b0 +
0&
0'
b0 (
#1850000
1"
b110 -
1'
#1860000
b11 +
1$
0'
b11 (
#1870000
b0 *
1'
#1880000
b10 +
b1 ,
0"
1%
0$
b0 -
0'
b10 (
0)
#1890000
1'
#1900000
b1 +
1&
0%
0'
b1 (
#1910000
b10 ,
b1 -
b1 *
1'
1)
#1920000
b11 +
0&
1$
0'
b11 (
#1930000
b11 ,
b10011 *
b10 -
1'
#1940000
b100 +
0$
1#
0'
b100 (
#1950000
b100 ,
b11 -
b100110100 *
1'
#1960000
b11 ,
b0 +
0#
0'
b0 (
#1970000
1'
#1980000
b100 ,
b11 +
1$
0'
b11 (
#1990000
b110 ,
b100 -
b1001101000011 *
1'
#2000000
b100 +
0$
1#
0'
b100 (
#2010000
1"
b11010000110100 *
b110 -
1'
#2020000
b11 +
1$
0#
0'
b11 (
#2030000
b0 *
1'
#2040000
b1 ,
0"
b0 -
0'
0)
#2050000
1'
#2060000
0'
#2070000
b10 ,
b11 *
b1 -
1'
1)
#2080000
b1 ,
b0 +
0$
0'
b0 (
#2090000
1'
#2100000
b10 ,
b10 +
1%
0'
b10 (
#2110000
b11 ,
b110010 *
b10 -
1'
#2120000
b11 +
0%
1$
0'
b11 (
#2130000
b100 ,
b11 -
b1100100011 *
1'
#2140000
b100 +
0$
1#
0'
b100 (
#2150000
b110 ,
b11001000110100 *
b100 -
1'
#2160000
b1 +
1&
0#
0'
b1 (
#2170000
1"
b110 -
b10001101000001 *
1'
#2180000
0'
#2190000
b0 *
1'
#2200000
b11 +
b1 ,
0"
0&
1$
b0 -
0'
b11 (
0)
#2210000
1'
#2220000
b0 ,
b0 +
0$
0'
b0 (
#2230000
1'
1)
#2240000
b1 ,
b1 +
1&
0'
b1 (
#2250000
b10 ,
b1 *
b1 -
1'
#2260000
b100 +
0&
1#
0'
b100 (
#2270000
b11 ,
b10 -
b10100 *
1'
#2280000
b10 +
1%
0#
0'
b10 (
#2290000
b100 ,
b101000010 *
b11 -
1'
#2300000
0'
#2310000
b110 ,
b100 -
b1010000100010 *
1'
#2320000
b1 +
1&
0%
0'
b1 (
#2330000
1"
b100001000100001 *
b110 -
1'
#2340000
0'
#2350000
b0 *
1'
#2360000
b1 ,
0"
b0 -
0'
0)
#2370000
1'
#2380000
b11 +
0&
1$
0'
b11 (
#2390000
b10 ,
b11 *
b1 -
1'
1)
#2400000
b100 +
0$
1#
0'
b100 (
#2410000
b11 ,
b10 -
b110100 *
1'
#2420000
b1 +
1&
0#
0'
b1 (
#2430000
b100 ,
b1101000001 *
b11 -
1'
#2440000
b100 +
0&
1#
0'
b100 (
#2450000
b110 ,
b100 -
b11010000010100 *
1'
#2460000
b1 +
1&
0#
0'
b1 (
#2470000
1"
b100000101000001 *
b110 -
1'
#2480000
b0 +
0&
0'
b0 (
#2490000
b0 *
1'
#2500000
b11 +
b1 ,
0"
1$
b0 -
0'
b11 (
0)
#2510000
1'
#2520000
b0 ,
b0 +
0$
0'
b0 (
#2530000
1'
1)
#2540000
b1 ,
b10 +
1%
0'
b10 (
#2550000
b10 ,
b1 -
b10 *
1'
#2560000
b1 +
1&
0%
0'
b1 (
#2570000
b11 ,
b100001 *
b10 -
1'
#2580000
b11 +
0&
1$
0'
b11 (
#2590000
b100 ,
b11 -
b1000010011 *
1'
#2600000
0'
#2610000
b110 ,
b10000100110011 *
b100 -
1'
#2620000
b0 +
0$
0'
b0 (
#2630000
1"
b110 -
1'
#2640000
b100 +
1#
0'
b100 (
#2650000
b0 *
1'
#2660000
b1 +
b1 ,
0"
1&
0#
b0 -
0'
b1 (
0)
#2670000
1'
#2680000
0'
#2690000
b10 ,
b1 -
b1 *
1'
1)
#2700000
b100 +
0&
1#
0'
b100 (
#2710000
b11 ,
b10100 *
b10 -
1'
#2720000
b11 +
1$
0#
0'
b11 (
#2730000
b100 ,
b11 -
b101000011 *
1'
#2740000
b11 ,
b0 +
0$
0'
b0 (
#2750000
1'
#2760000
b100 ,
b1 +
1&
0'
b1 (
#2770000
b110 ,
b100 -
b1010000110001 *
1'
#2780000
b10 +
0&
1%
0'
b10 (
#2790000
1"
b100001100010010 *
b110 -
1'
#2800000
b100 +
0%
1#
0'
b100 (
#2810000
b0 *
1'
#2820000
b1 ,
0"
b0 -
0'
0)
#2830000
1'
#2840000
0'
#2850000
b10 ,
b100 *
b1 -
1'
1)
#2860000
b1 ,
b0 +
0#
0'
b0 (
#2870000
1'
#2880000
b10 ,
b11 +
1$
0'
b11 (
#2890000
b11 ,
b1000011 *
b10 -
1'
#2900000
b100 +
0$
1#
0'
b100 (
#2910000
b100 ,
b11 -
b10000110100 *
1'
#2920000
b1 +
1&
0#
0'
b1 (
#2930000
b110 ,
b100001101000001 *
b100 -
1'
#2940000
0'
#2950000
1"
b110 -
b11010000010001 *
1'
#2960000
0'
#2970000
b0 *
1'
#2980000
b1 ,
0"
b0 -
0'
0)
#2990000
1'
#3000000
b10 +
0&
1%
0'
b10 (
#3010000
b10 ,
b1 -
b10 *
1'
1)
#3020000
b100 +
0%
1#
0'
b100 (
#3030000
b11 ,
b100100 *
b10 -
1'
#3040000
b11 +
1$
0#
0'
b11 (
#3050000
b100 ,
b11 -
b1001000011 *
1'
#3060000
b11 ,
b0 +
0$
0'
b0 (
#3070000
1'
#3080000
0'
#3090000
1'
#3100000
b100 ,
b1 +
1&
0'
b1 (
#3110000
b101 ,
b10010000110001 *
b100 -
1'
#3120000
b11 +
0&
1$
0'
b11 (
#3130000
1!
b101 -
b100001100010011 *
1'
#3140000
b1 +
1&
0$
0'
b1 (
#3150000
b0 *
1'
#3160000
b10 +
b1 ,
0!
0&
1%
b0 -
0'
b10 (
0)
#3170000
1'
#3180000
0'
#3190000
b10 ,
b1 -
b10 *
1'
1)
#3200000
b1 +
1&
0%
0'
b1 (
#3210000
b11 ,
b100001 *
b10 -
1'
#3220000
b100 +
0&
1#
0'
b100 (
#3230000
b100 ,
b11 -
b1000010100 *
1'
#3240000
b1 +
1&
0#
0'
b1 (
#3250000
b110 ,
b10000101000001 *
b100 -
1'
#3260000
0'
#3270000
1"
b110 -
b1010000010001 *
1'
#3280000
b11 +
0&
1$
0'
b11 (
#3290000
b0 *
1'
#3300000
b1 +
b1 ,
0"
1&
0$
b0 -
0'
b1 (
0)
#3310000
1'
#3320000
b0 ,
b0 +
0&
0'
b0 (
#3330000
1'
1)
#3340000
b1 ,
b10 +
1%
0'
b10 (
#3350000
b10 ,
b10 *
b1 -
1'
#3360000
b1 +
1&
0%
0'
b1 (
#3370000
b11 ,
b10 -
b100001 *
1'
#3380000
b10 ,
b0 +
0&
0'
b0 (
#3390000
1'
#3400000
b11 ,
b1 +
1&
0'
b1 (
#3410000
b100 ,
b11 -
b1000010001 *
1'
#3420000
b100 +
0&
1#
0'
b100 (
#3430000
b110 ,
b10000100010100 *
b100 -
1'
#3440000
b10 +
1%
0#
0'
b10 (
#3450000
1"
b110 -
b1000101000010 *
1'
#3460000
b0 +
0%
0'
b0 (
#3470000
b0 *
1'
#3480000
b0 ,
0"
b0 -
0'
0)
#3490000
1'
#3500000
b1 ,
b11 +
1$
0'
b11 (
#3510000
b10 ,
b1 -
b11 *
1'
1)
#3520000
b10 +
1%
0$
0'
b10 (
#3530000
b11 ,
b110010 *
b10 -
1'
#3540000
b100 +
0%
1#
0'
b100 (
#3550000
b100 ,
b11 -
b1100100100 *
1'
#3560000
b11 ,
b0 +
0#
0'
b0 (
#3570000
1'
#3580000
b100 ,
b11 +
1$
0'
b11 (
#3590000
b110 ,
b100 -
b11001001000011 *
1'
#3600000
b10 +
1%
0$
0'
b10 (
#3610000
1"
b10010000110010 *
b110 -
1'
#3620000
b1 +
1&
0%
0'
b1 (
#3630000
b0 *
1'
#3640000
b100 +
b1 ,
0"
0&
1#
b0 -
0'
b100 (
0)
#3650000
1'
#3660000
b0 ,
b0 +
0#
0'
b0 (
#3670000
1'
1)
#3680000
b1 ,
b100 +
1#
0'
b100 (
#3690000
b10 ,
b1 -
b100 *
1'
#3700000
0'
#3710000
b11 ,
b1000100 *
b10 -
1'
#3720000
b11 +
1$
0#
0'
b11 (
#3730000
b100 ,
b11 -
b10001000011 *
1'
#3740000
0'
#3750000
b110 ,
b100010000110011 *
b100 -
1'
#3760000
b10 +
1%
0$
0'
b10 (
#3770000
1"
b110 -
b100001100110010 *
1'
#3780000
b1 +
1&
0%
0'
b1 (
#3790000
b0 *
1'
#3800000
b0 +
b0 ,
0"
0&
b0 -
0'
b0 (
0)
#3810000
1'
#3820000
0'
#3830000
1'
1)
#3840000
b1 ,
b11 +
1$
0'
b11 (
#3850000
b10 ,
b11 *
b1 -
1'
#3860000
b100 +
0$
1#
0'
b100 (
#3870000
b11 ,
b10 -
b110100 *
1'
#3880000
b10 ,
b0 +
0#
0'
b0 (
#3890000
1'
#3900000
0'
#3910000
1'
#3920000
b11 ,
b1 +
1&
0'
b1 (
#3930000
b100 ,
b1101000001 *
b11 -
1'
#3940000
0'
#3950000
b110 ,
b100 -
b11010000010001 *
1'
#3960000
b100 +
0&
1#
0'
b100 (
#3970000
1"
b100000100010100 *
b110 -
1'
#3980000
b1 +
1&
0#
0'
b1 (
#3990000
b0 *
1'
#4000000
b100 +
b1 ,
0"
0&
1#
b0 -
0'
b100 (
0)
#4010000
1'
#4020000
b0 ,
b0 +
0#
0'
b0 (
#4030000
1'
1)
#4040000
b1 ,
b10 +
1%
0'
b10 (
#4050000
b10 ,
b1 -
b10 *
1'
#4060000
b1 +
1&
0%
0'
b1 (
#4070000
b11 ,
b100001 *
b10 -
1'
#4080000
b11 +
0&
1$
0'
b11 (
#4090000
b100 ,
b11 -
b1000010011 *
1'
#4100000
b1 +
1&
0$
0'
b1 (
#4110000
b110 ,
b10000100110001 *
b100 -
1'
#4120000
b11 +
0&
1$
0'
b11 (
#4130000
1"
b110 -
b1001100010011 *
1'
#4140000
0'
#4150000
b0 *
1'
#4160000
b10 +
b1 ,
0"
1%
0$
b0 -
0'
b10 (
0)
#4170000
1'
#4180000
b11 +
0%
1$
0'
b11 (
#4190000
b10 ,
b1 -
b11 *
1'
1)
#4200000
b1 +
1&
0$
0'
b1 (
#4210000
b11 ,
b110001 *
b10 -
1'
#4220000
0'
#4230000
b100 ,
b11 -
b1100010001 *
1'
#4240000
b10 +
0&
1%
0'
b10 (
#4250000
b110 ,
b11000100010010 *
b100 -
1'
#4260000
b100 +
0%
1#
0'
b100 (
#4270000
1"
b110 -
b1000100100100 *
1'
#4280000
b11 +
1$
0#
0'
b11 (
#4290000
b0 *
1'
#4300000
b100 +
b1 ,
0"
0$
1#
b0 -
0'
b100 (
0)
#4310000
1'
#4320000
b1 +
1&
0#
0'
b1 (
#4330000
b10 ,
b1 -
b1 *
1'
1)
#4340000
b10 +
0&
1%
0'
b10 (
#4350000
b11 ,
b10010 *
b10 -
1'
#4360000
0'
#4370000
b100 ,
b11 -
b100100010 *
1'
#4380000
0'
#4390000
b110 ,
b1001000100010 *
b100 -
1'
#4400000
b1 +
1&
0%
0'
b1 (
#4410000
1"
b110 -
b10001000100001 *
1'
#4420000
b10 +
0&
1%
0'
b10 (
#4430000
b0 *
1'
#4440000
b100 +
b1 ,
0"
0%
1#
b0 -
0'
b100 (
0)
#4450000
1'
#4460000
0'
#4470000
b10 ,
b1 -
b100 *
1'
1)
#4480000
b1 +
1&
0#
0'
b1 (
#4490000
b11 ,
b1000001 *
b10 -
1'
#4500000
b100 +
0&
1#
0'
b100 (
#4510000
b100 ,
b11 -
b10000010100 *
1'
#4520000
b10 +
1%
0#
0'
b10 (
#4530000
b110 ,
b100000101000010 *
b100 -
1'
#4540000
0'
#4550000
1"
b110 -
b1010000100010 *
1'
#4560000
b11 +
0%
1$
0'
b11 (
#4570000
b0 *
1'
#4580000
b1 +
b1 ,
0"
1&
0$
b0 -
0'
b1 (
0)
#4590000
1'
#4600000
b11 +
0&
1$
0'
b11 (
#4610000
b10 ,
b1 -
b11 *
1'
1)
#4620000
b1 ,
b0 +
0$
0'
b0 (
#4630000
1'
#4640000
b10 ,
b1 +
1&
0'
b1 (
#4650000
b11 ,
b10 -
b110001 *
1'
#4660000
b10 +
0&
1%
0'
b10 (
#4670000
b100 ,
b1100010010 *
b11 -
1'
#4680000
b1 +
1&
0%
0'
b1 (
#4690000
b110 ,
b100 -
b11000100100001 *
1'
#4700000
b10 +
0&
1%
0'
b10 (
#4710000
1"
b1001000010010 *
b110 -
1'
#4720000
b0 +
0%
0'
b0 (
#4730000
b0 *
1'
#4740000
b1 +
b1 ,
0"
1&
b0 -
0'
b1 (
0)
#4750000
1'
#4760000
b100 +
0&
1#
0'
b100 (
#4770000
b10 ,
b100 *
b1 -
1'
1)
#4780000
0'
#4790000
b11 ,
b10 -
b1000100 *
1'
#4800000
b11 +
1$
0#
0'
b11 (
#4810000
b100 ,
b10001000011 *
b11 -
1'
#4820000
b10 +
1%
0$
0'
b10 (
#4830000
b110 ,
b100 -
b100010000110010 *
1'
#4840000
b1 +
1&
0%
0'
b1 (
#4850000
1"
b100001100100001 *
b110 -
1'
#4860000
b10 +
0&
1%
0'
b10 (
#4870000
b0 *
1'
#4880000
b1 ,
0"
b0 -
0'
0)
#4890000
1'
#4900000
0'
#4910000
b10 ,
b10 *
b1 -
1'
1)
#4920000
0'
#4930000
b11 ,
b10 -
b100010 *
1'
#4940000
b1 +
1&
0%
0'
b1 (
#4950000
b100 ,
b1000100001 *
b11 -
1'
#4960000
b11 +
0&
1$
0'
b11 (
#4970000
b110 ,
b100 -
b10001000010011 *
1'
#4980000
b100 +
0$
1#
0'
b100 (
#4990000
1"
b10000100110100 *
b110 -
1'
#5000000
b11 +
1$
0#
0'
b11 (
#5010000
b0 *
1'
#5020000
b0 +
b0 ,
0"
0$
b0 -
0'
b0 (
0)
#5030000
1'
#5040000
b1 ,
b10 +
1%
0'
b10 (
#5050000
b10 ,
b10 *
b1 -
1'
1)
#5060000
b1 +
1&
0%
0'
b1 (
#5070000
b11 ,
b10 -
b100001 *
1'
#5080000
b10 +
0&
1%
0'
b10 (
#5090000
b100 ,
b1000010010 *
b11 -
1'
#5100000
b11 ,
b0 +
0%
0'
b0 (
#5110000
1'
#5120000
b100 ,
b1 +
1&
0'
b1 (
#5130000
b110 ,
b10000100100001 *
b100 -
1'
#5140000
0'
#5150000
1"
b110 -
b1001000010001 *
1'
#5160000
b10 +
0&
1%
0'
b10 (
#5170000
b0 *
1'
#5180000
b100 +
b1 ,
0"
0%
1#
b0 -
0'
b100 (
0)
#5190000
1'
#5200000
b0 ,
b0 +
0#
0'
b0 (
#5210000
1'
1)
#5220000
b1 ,
b1 +
1&
0'
b1 (
#5230000
b10 ,
b1 *
b1 -
1'
#5240000
0'
#5250000
b11 ,
b10 -
b10001 *
1'
#5260000
b10 ,
b0 +
0&
0'
b0 (
#5270000
1'
#5280000
0'
#5290000
1'
#5300000
b11 ,
b10 +
1%
0'
b10 (
#5310000
b100 ,
b100010010 *
b11 -
1'
#5320000
b11 +
0%
1$
0'
b11 (
#5330000
b110 ,
b100 -
b1000100100011 *
1'
#5340000
0'
#5350000
1"
b1001000110011 *
b110 -
1'
#5360000
b1 +
1&
0$
0'
b1 (
#5370000
b0 *
1'
#5380000
b100 +
b1 ,
0"
0&
1#
b0 -
0'
b100 (
0)
#5390000
1'
#5400000
b0 ,
b0 +
0#
0'
b0 (
#5410000
1'
1)
#5420000
b1 ,
b11 +
1$
0'
b11 (
#5430000
b10 ,
b1 -
b11 *
1'
#5440000
b10 +
1%
0$
0'
b10 (
#5450000
b11 ,
b110010 *
b10 -
1'
#5460000
b1 +
1&
0%
0'
b1 (
#5470000
b100 ,
b11 -
b1100100001 *
1'
#5480000
0'
#5490000
b110 ,
b11001000010001 *
b100 -
1'
#5500000
b0 +
0&
0'
b0 (
#5510000
1"
b110 -
1'
#5520000
0'
#5530000
b0 *
1'
#5540000
b100 +
b1 ,
0"
1#
b0 -
0'
b100 (
0)
#5550000
1'
#5560000
b0 ,
b0 +
0#
0'
b0 (
#5570000
1'
1)
#5580000
b1 ,
b10 +
1%
0'
b10 (
#5590000
b10 ,
b10 *
b1 -
1'
#5600000
0'
#5610000
b11 ,
b10 -
b100010 *
1'
#5620000
b1 +
1&
0%
0'
b1 (
#5630000
b100 ,
b1000100001 *
b11 -
1'
#5640000
b11 ,
b0 +
0&
0'
b0 (
#5650000
1'
#5660000
0'
#5670000
1'
#5680000
b100 ,
b11 +
1$
0'
b11 (
#5690000
b110 ,
b100 -
b10001000010011 *
1'
#5700000
b1 +
1&
0$
0'
b1 (
#5710000
1"
b10000100110001 *
b110 -
1'
#5720000
0'
#5730000
b0 *
1'
#5740000
b0 +
b0 ,
0"
0&
b0 -
0'
b0 (
0)
#5750000
1'
#5760000
0'
#5770000
1'
1)
#5780000
b1 ,
b100 +
1#
0'
b100 (
#5790000
b10 ,
b1 -
b100 *
1'
#5800000
b11 +
1$
0#
0'
b11 (
#5810000
b11 ,
b1000011 *
b10 -
1'
#5820000
b100 +
0$
1#
0'
b100 (
#5830000
b100 ,
b11 -
b10000110100 *
1'
#5840000
b1 +
1&
0#
0'
b1 (
#5850000
b110 ,
b100001101000001 *
b100 -
1'
#5860000
b10 +
0&
1%
0'
b10 (
#5870000
1"
b110 -
b11010000010010 *
1'
#5880000
b11 +
0%
1$
0'
b11 (
#5890000
b0 *
1'
#5900000
b10 +
b1 ,
0"
1%
0$
b0 -
0'
b10 (
0)
#5910000
1'
#5920000
b0 ,
b0 +
0%
0'
b0 (
#5930000
1'
1)
#5940000
b1 ,
b100 +
1#
0'
b100 (
#5950000
b10 ,
b100 *
b1 -
1'
#5960000
b1 +
1&
0#
0'
b1 (
#5970000
b11 ,
b10 -
b1000001 *
1'
#5980000
b100 +
0&
1#
0'
b100 (
#5990000
b100 ,
b10000010100 *
b11 -
1'
#6000000
b11 ,
b0 +
0#
0'
b0 (
#6010000
1'
#6020000
b100 ,
b1 +
1&
0'
b1 (
#6030000
b110 ,
b100000101000001 *
b100 -
1'
#6040000
0'
#6050000
1"
b110 -
b1010000010001 *
1'
#6060000
b10 +
0&
1%
0'
b10 (
#6070000
b0 *
1'
