6-2/user/src/top.v
module string01011_moore (clk, reset, X, Z);
    input clk, reset, X;
    output Z;
  
    parameter   IDLE    = 5'b00000,  
                S1      = 5'b00001,     // 0
                S2      = 5'b00010,     // 01 
                S3      = 5'b00100,     // 010
                S4      = 5'b01000,     // 0101
                S5      = 5'b10000;     // 01011

    reg [4:0] state, next_state;

    always @(posedge clk, negedge reset) begin
        if (reset == 1'b0)
            state <= S1;
        else begin
            state <= next_state;
        end
    end

    always @(*) begin
        case (state)
            IDLE :
                if (X == 0)
                    next_state = S1;
                else
                    next_state = IDLE;
            S1 :
                if (X == 1)
                    next_state = S2;
                else if (X == 0)
                    next_state = S1;
                else
                    next_state = IDLE;
            S2 :
                if (X == 0)
                    next_state = S3;
                else
                    next_state = IDLE;
            S3 :
                if (X == 1)
                    next_state = S4;
                else if (X == 0)
                    next_state = S1;
                else
                    next_state = IDLE;
            S4 :
                if (X == 1)
                    next_state = S5;
                else if (X == 0)
                    next_state = S3;
                else
                    next_state = IDLE;
            S5 : 
                if (X == 0)
                    next_state = S1;
                else
                    next_state = IDLE;
            default :
                next_state = IDLE;
        endcase
    end

    assign Z = (state == S5) ? 1'b1 : 1'b0;

endmodule

6-2/user/sim/tb.v
`timescale 1ns/1ps
module tb ();

    initial begin
       $dumpfile("wave.vcd");
       $dumpvars(0, tb);
       #6000 $finish;
    end

    reg X, clk = 1'b0, reset = 1'b1;

    always 
        #10 clk <= ~clk;

    always 
        #20 X <= $random();

    initial begin
        #10 reset = 1'b0;
        #10 reset = 1'b1;
    end

    wire Z;

    string01011_moore u_string01011_moore(
        //ports
        .clk   		( clk   		),
        .reset 		( reset 		),
        .X     		( X     		),
        .Z     		( Z     		)
    );

endmodule

6-2/wave.vcd
$date
	Sat Apr 16 13:10:41 2022
$end
$version
	Icarus Verilog
$end
$timescale
	1ps
$end
$scope module tb $end
$var wire 1 ! Z $end
$var reg 1 " X $end
$var reg 1 # clk $end
$var reg 1 $ reset $end
$scope module u_string01011_moore $end
$var wire 1 " X $end
$var wire 1 # clk $end
$var wire 1 $ reset $end
$var wire 1 ! Z $end
$var reg 5 % next_state [4:0] $end
$var reg 5 & state [4:0] $end
$upscope $end
$upscope $end
$enddefinitions $end
#0
$dumpvars
bx &
bx %
1$
0#
x"
x!
$end
#10000
b0 %
0!
b1 &
1#
0$
#20000
b1 %
0#
0"
1$
#30000
1#
#40000
b10 %
0#
1"
#50000
b0 %
b10 &
1#
#60000
0#
#70000
b0 &
1#
#80000
0#
#90000
1#
#100000
0#
#110000
1#
#120000
0#
#130000
1#
#140000
0#
#150000
1#
#160000
b1 %
0#
0"
#170000
b1 &
1#
#180000
b10 %
0#
1"
#190000
b0 %
b10 &
1#
#200000
0#
#210000
b0 &
1#
#220000
b1 %
0#
0"
#230000
b1 &
1#
#240000
b10 %
0#
1"
#250000
b0 %
b10 &
1#
#260000
0#
#270000
b0 &
1#
#280000
b1 %
0#
0"
#290000
b1 &
1#
#300000
b10 %
0#
1"
#310000
b0 %
b10 &
1#
#320000
b100 %
0#
0"
#330000
b1 %
b100 &
1#
#340000
b1000 %
0#
1"
#350000
b10000 %
b1000 &
1#
#360000
b100 %
0#
0"
#370000
b1 %
b100 &
1#
#380000
b1000 %
0#
1"
#390000
b10000 %
b1000 &
1#
#400000
0#
#410000
b0 %
1!
b10000 &
1#
#420000
b1 %
0#
0"
#430000
0!
b1 &
1#
#440000
b10 %
0#
1"
#450000
b0 %
b10 &
1#
#460000
b100 %
0#
0"
#470000
b1 %
b100 &
1#
#480000
0#
#490000
b1 &
1#
#500000
0#
#510000
1#
#520000
b10 %
0#
1"
#530000
b0 %
b10 &
1#
#540000
b100 %
0#
0"
#550000
b1 %
b100 &
1#
#560000
b1000 %
0#
1"
#570000
b10000 %
b1000 &
1#
#580000
0#
#590000
b0 %
1!
b10000 &
1#
#600000
0#
#610000
0!
b0 &
1#
#620000
0#
#630000
1#
#640000
b1 %
0#
0"
#650000
b1 &
1#
#660000
0#
#670000
1#
#680000
0#
#690000
1#
#700000
0#
#710000
1#
#720000
b10 %
0#
1"
#730000
b0 %
b10 &
1#
#740000
b100 %
0#
0"
#750000
b1 %
b100 &
1#
#760000
b1000 %
0#
1"
#770000
b10000 %
b1000 &
1#
#780000
0#
#790000
b0 %
1!
b10000 &
1#
#800000
0#
#810000
0!
b0 &
1#
#820000
0#
#830000
1#
#840000
0#
#850000
1#
#860000
b1 %
0#
0"
#870000
b1 &
1#
#880000
0#
#890000
1#
#900000
b10 %
0#
1"
#910000
b0 %
b10 &
1#
#920000
0#
#930000
b0 &
1#
#940000
0#
#950000
1#
#960000
b1 %
0#
0"
#970000
b1 &
1#
#980000
0#
#990000
1#
#1000000
0#
#1010000
1#
#1020000
0#
#1030000
1#
#1040000
0#
#1050000
1#
#1060000
b10 %
0#
1"
#1070000
b0 %
b10 &
1#
#1080000
b100 %
0#
0"
#1090000
b1 %
b100 &
1#
#1100000
0#
#1110000
b1 &
1#
#1120000
b10 %
0#
1"
#1130000
b0 %
b10 &
1#
#1140000
0#
#1150000
b0 &
1#
#1160000
b1 %
0#
0"
#1170000
b1 &
1#
#1180000
0#
#1190000
1#
#1200000
0#
#1210000
1#
#1220000
0#
#1230000
1#
#1240000
0#
#1250000
1#
#1260000
b10 %
0#
1"
#1270000
b0 %
b10 &
1#
#1280000
0#
#1290000
b0 &
1#
#1300000
0#
#1310000
1#
#1320000
0#
#1330000
1#
#1340000
0#
#1350000
1#
#1360000
b1 %
0#
0"
#1370000
b1 &
1#
#1380000
0#
#1390000
1#
#1400000
b10 %
0#
1"
#1410000
b0 %
b10 &
1#
#1420000
0#
#1430000
b0 &
1#
#1440000
0#
#1450000
1#
#1460000
b1 %
0#
0"
#1470000
b1 &
1#
#1480000
0#
#1490000
1#
#1500000
b10 %
0#
1"
#1510000
b0 %
b10 &
1#
#1520000
0#
#1530000
b0 &
1#
#1540000
b1 %
0#
0"
#1550000
b1 &
1#
#1560000
b10 %
0#
1"
#1570000
b0 %
b10 &
1#
#1580000
0#
#1590000
b0 &
1#
#1600000
b1 %
0#
0"
#1610000
b1 &
1#
#1620000
b10 %
0#
1"
#1630000
b0 %
b10 &
1#
#1640000
0#
#1650000
b0 &
1#
#1660000
0#
#1670000
1#
#1680000
b1 %
0#
0"
#1690000
b1 &
1#
#1700000
b10 %
0#
1"
#1710000
b0 %
b10 &
1#
#1720000
0#
#1730000
b0 &
1#
#1740000
b1 %
0#
0"
#1750000
b1 &
1#
#1760000
0#
#1770000
1#
#1780000
0#
#1790000
1#
#1800000
0#
#1810000
1#
#1820000
b10 %
0#
1"
#1830000
b0 %
b10 &
1#
#1840000
0#
#1850000
b0 &
1#
#1860000
b1 %
0#
0"
#1870000
b1 &
1#
#1880000
0#
#1890000
1#
#1900000
b10 %
0#
1"
#1910000
b0 %
b10 &
1#
#1920000
0#
#1930000
b0 &
1#
#1940000
0#
#1950000
1#
#1960000
0#
#1970000
1#
#1980000
0#
#1990000
1#
#2000000
b1 %
0#
0"
#2010000
b1 &
1#
#2020000
b10 %
0#
1"
#2030000
b0 %
b10 &
1#
#2040000
0#
#2050000
b0 &
1#
#2060000
0#
#2070000
1#
#2080000
b1 %
0#
0"
#2090000
b1 &
1#
#2100000
0#
#2110000
1#
#2120000
0#
#2130000
1#
#2140000
0#
#2150000
1#
#2160000
0#
#2170000
1#
#2180000
0#
#2190000
1#
#2200000
0#
#2210000
1#
#2220000
b10 %
0#
1"
#2230000
b0 %
b10 &
1#
#2240000
0#
#2250000
b0 &
1#
#2260000
0#
#2270000
1#
#2280000
0#
#2290000
1#
#2300000
0#
#2310000
1#
#2320000
b1 %
0#
0"
#2330000
b1 &
1#
#2340000
b10 %
0#
1"
#2350000
b0 %
b10 &
1#
#2360000
0#
#2370000
b0 &
1#
#2380000
b1 %
0#
0"
#2390000
b1 &
1#
#2400000
0#
#2410000
1#
#2420000
b10 %
0#
1"
#2430000
b0 %
b10 &
1#
#2440000
0#
#2450000
b0 &
1#
#2460000
b1 %
0#
0"
#2470000
b1 &
1#
#2480000
b10 %
0#
1"
#2490000
b0 %
b10 &
1#
#2500000
0#
#2510000
b0 &
1#
#2520000
0#
#2530000
1#
#2540000
0#
#2550000
1#
#2560000
b1 %
0#
0"
#2570000
b1 &
1#
#2580000
0#
#2590000
1#
#2600000
0#
#2610000
1#
#2620000
b10 %
0#
1"
#2630000
b0 %
b10 &
1#
#2640000
b100 %
0#
0"
#2650000
b1 %
b100 &
1#
#2660000
0#
#2670000
b1 &
1#
#2680000
0#
#2690000
1#
#2700000
b10 %
0#
1"
#2710000
b0 %
b10 &
1#
#2720000
0#
#2730000
b0 &
1#
#2740000
b1 %
0#
0"
#2750000
b1 &
1#
#2760000
0#
#2770000
1#
#2780000
b10 %
0#
1"
#2790000
b0 %
b10 &
1#
#2800000
b100 %
0#
0"
#2810000
b1 %
b100 &
1#
#2820000
0#
#2830000
b1 &
1#
#2840000
0#
#2850000
1#
#2860000
b10 %
0#
1"
#2870000
b0 %
b10 &
1#
#2880000
b100 %
0#
0"
#2890000
b1 %
b100 &
1#
#2900000
0#
#2910000
b1 &
1#
#2920000
b10 %
0#
1"
#2930000
b0 %
b10 &
1#
#2940000
b100 %
0#
0"
#2950000
b1 %
b100 &
1#
#2960000
b1000 %
0#
1"
#2970000
b10000 %
b1000 &
1#
#2980000
0#
#2990000
b0 %
1!
b10000 &
1#
#3000000
0#
#3010000
0!
b0 &
1#
#3020000
0#
#3030000
1#
#3040000
0#
#3050000
1#
#3060000
b1 %
0#
0"
#3070000
b1 &
1#
#3080000
0#
#3090000
1#
#3100000
0#
#3110000
1#
#3120000
b10 %
0#
1"
#3130000
b0 %
b10 &
1#
#3140000
b100 %
0#
0"
#3150000
b1 %
b100 &
1#
#3160000
0#
#3170000
b1 &
1#
#3180000
b10 %
0#
1"
#3190000
b0 %
b10 &
1#
#3200000
0#
#3210000
b0 &
1#
#3220000
b1 %
0#
0"
#3230000
b1 &
1#
#3240000
0#
#3250000
1#
#3260000
0#
#3270000
1#
#3280000
b10 %
0#
1"
#3290000
b0 %
b10 &
1#
#3300000
0#
#3310000
b0 &
1#
#3320000
b1 %
0#
0"
#3330000
b1 &
1#
#3340000
0#
#3350000
1#
#3360000
0#
#3370000
1#
#3380000
b10 %
0#
1"
#3390000
b0 %
b10 &
1#
#3400000
0#
#3410000
b0 &
1#
#3420000
b1 %
0#
0"
#3430000
b1 &
1#
#3440000
0#
#3450000
1#
#3460000
0#
#3470000
1#
#3480000
b10 %
0#
1"
#3490000
b0 %
b10 &
1#
#3500000
b100 %
0#
0"
#3510000
b1 %
b100 &
1#
#3520000
0#
#3530000
b1 &
1#
#3540000
b10 %
0#
1"
#3550000
b0 %
b10 &
1#
#3560000
b100 %
0#
0"
#3570000
b1 %
b100 &
1#
#3580000
0#
#3590000
b1 &
1#
#3600000
0#
#3610000
1#
#3620000
b10 %
0#
1"
#3630000
b0 %
b10 &
1#
#3640000
b100 %
0#
0"
#3650000
b1 %
b100 &
1#
#3660000
b1000 %
0#
1"
#3670000
b10000 %
b1000 &
1#
#3680000
0#
#3690000
b0 %
1!
b10000 &
1#
#3700000
b1 %
0#
0"
#3710000
0!
b1 &
1#
#3720000
0#
#3730000
1#
#3740000
0#
#3750000
1#
#3760000
0#
#3770000
1#
#3780000
b10 %
0#
1"
#3790000
b0 %
b10 &
1#
#3800000
b100 %
0#
0"
#3810000
b1 %
b100 &
1#
#3820000
0#
#3830000
b1 &
1#
#3840000
0#
#3850000
1#
#3860000
0#
#3870000
1#
#3880000
b10 %
0#
1"
#3890000
b0 %
b10 &
1#
#3900000
0#
#3910000
b0 &
1#
#3920000
0#
#3930000
1#
#3940000
b1 %
0#
0"
#3950000
b1 &
1#
#3960000
b10 %
0#
1"
#3970000
b0 %
b10 &
1#
#3980000
0#
#3990000
b0 &
1#
#4000000
0#
#4010000
1#
#4020000
b1 %
0#
0"
#4030000
b1 &
1#
#4040000
0#
#4050000
1#
#4060000
b10 %
0#
1"
#4070000
b0 %
b10 &
1#
#4080000
0#
#4090000
b0 &
1#
#4100000
0#
#4110000
1#
#4120000
0#
#4130000
1#
#4140000
0#
#4150000
1#
#4160000
b1 %
0#
0"
#4170000
b1 &
1#
#4180000
b10 %
0#
1"
#4190000
b0 %
b10 &
1#
#4200000
0#
#4210000
b0 &
1#
#4220000
b1 %
0#
0"
#4230000
b1 &
1#
#4240000
0#
#4250000
1#
#4260000
0#
#4270000
1#
#4280000
0#
#4290000
1#
#4300000
b10 %
0#
1"
#4310000
b0 %
b10 &
1#
#4320000
0#
#4330000
b0 &
1#
#4340000
b1 %
0#
0"
#4350000
b1 &
1#
#4360000
0#
#4370000
1#
#4380000
b10 %
0#
1"
#4390000
b0 %
b10 &
1#
#4400000
b100 %
0#
0"
#4410000
b1 %
b100 &
1#
#4420000
0#
#4430000
b1 &
1#
#4440000
b10 %
0#
1"
#4450000
b0 %
b10 &
1#
#4460000
b100 %
0#
0"
#4470000
b1 %
b100 &
1#
#4480000
0#
#4490000
b1 &
1#
#4500000
b10 %
0#
1"
#4510000
b0 %
b10 &
1#
#4520000
b100 %
0#
0"
#4530000
b1 %
b100 &
1#
#4540000
0#
#4550000
b1 &
1#
#4560000
b10 %
0#
1"
#4570000
b0 %
b10 &
1#
#4580000
0#
#4590000
b0 &
1#
#4600000
0#
#4610000
1#
#4620000
b1 %
0#
0"
#4630000
b1 &
1#
#4640000
0#
#4650000
1#
#4660000
0#
#4670000
1#
#4680000
b10 %
0#
1"
#4690000
b0 %
b10 &
1#
#4700000
b100 %
0#
0"
#4710000
b1 %
b100 &
1#
#4720000
0#
#4730000
b1 &
1#
#4740000
b10 %
0#
1"
#4750000
b0 %
b10 &
1#
#4760000
b100 %
0#
0"
#4770000
b1 %
b100 &
1#
#4780000
0#
#4790000
b1 &
1#
#4800000
0#
#4810000
1#
#4820000
0#
#4830000
1#
#4840000
b10 %
0#
1"
#4850000
b0 %
b10 &
1#
#4860000
b100 %
0#
0"
#4870000
b1 %
b100 &
1#
#4880000
0#
#4890000
b1 &
1#
#4900000
0#
#4910000
1#
#4920000
b10 %
0#
1"
#4930000
b0 %
b10 &
1#
#4940000
0#
#4950000
b0 &
1#
#4960000
b1 %
0#
0"
#4970000
b1 &
1#
#4980000
b10 %
0#
1"
#4990000
b0 %
b10 &
1#
#5000000
0#
#5010000
b0 &
1#
#5020000
0#
#5030000
1#
#5040000
0#
#5050000
1#
#5060000
b1 %
0#
0"
#5070000
b1 &
1#
#5080000
b10 %
0#
1"
#5090000
b0 %
b10 &
1#
#5100000
0#
#5110000
b0 &
1#
#5120000
0#
#5130000
1#
#5140000
b1 %
0#
0"
#5150000
b1 &
1#
#5160000
0#
#5170000
1#
#5180000
b10 %
0#
1"
#5190000
b0 %
b10 &
1#
#5200000
b100 %
0#
0"
#5210000
b1 %
b100 &
1#
#5220000
0#
#5230000
b1 &
1#
#5240000
b10 %
0#
1"
#5250000
b0 %
b10 &
1#
#5260000
0#
#5270000
b0 &
1#
#5280000
b1 %
0#
0"
#5290000
b1 &
1#
#5300000
0#
#5310000
1#
#5320000
b10 %
0#
1"
#5330000
b0 %
b10 &
1#
#5340000
b100 %
0#
0"
#5350000
b1 %
b100 &
1#
#5360000
0#
#5370000
b1 &
1#
#5380000
b10 %
0#
1"
#5390000
b0 %
b10 &
1#
#5400000
b100 %
0#
0"
#5410000
b1 %
b100 &
1#
#5420000
b1000 %
0#
1"
#5430000
b10000 %
b1000 &
1#
#5440000
0#
#5450000
b0 %
1!
b10000 &
1#
#5460000
b1 %
0#
0"
#5470000
0!
b1 &
1#
#5480000
b10 %
0#
1"
#5490000
b0 %
b10 &
1#
#5500000
b100 %
0#
0"
#5510000
b1 %
b100 &
1#
#5520000
b1000 %
0#
1"
#5530000
b10000 %
b1000 &
1#
#5540000
b100 %
0#
0"
#5550000
b1 %
b100 &
1#
#5560000
0#
#5570000
b1 &
1#
#5580000
b10 %
0#
1"
#5590000
b0 %
b10 &
1#
#5600000
b100 %
0#
0"
#5610000
b1 %
b100 &
1#
#5620000
0#
#5630000
b1 &
1#
#5640000
0#
#5650000
1#
#5660000
b10 %
0#
1"
#5670000
b0 %
b10 &
1#
#5680000
0#
#5690000
b0 &
1#
#5700000
0#
#5710000
1#
#5720000
0#
#5730000
1#
#5740000
0#
#5750000
1#
#5760000
b1 %
0#
0"
#5770000
b1 &
1#
#5780000
b10 %
0#
1"
#5790000
b0 %
b10 &
1#
#5800000
0#
#5810000
b0 &
1#
#5820000
0#
#5830000
1#
#5840000
b1 %
0#
0"
#5850000
b1 &
1#
#5860000
0#
#5870000
1#
#5880000
0#
#5890000
1#
#5900000
0#
#5910000
1#
#5920000
0#
#5930000
1#
#5940000
0#
#5950000
1#
#5960000
b10 %
0#
1"
#5970000
b0 %
b10 &
1#
#5980000
0#
#5990000
b0 &
1#
